xerial/AsyncDBSessionBase.py
xerial/AsyncDBSessionPool.py
xerial/AsyncMSSQLDBSession.py
xerial/AsyncMariaDBSession.py
xerial/AsyncOracleDBSession.py
xerial/AsyncPostgresDBSession.py
xerial/AsyncRoundRobinConnector.py
xerial/AsyncSQLiteDBSession.py
xerial/Children.py
xerial/Column.py
xerial/ColumnType.py
xerial/Currency.py
xerial/CurrencyColumn.py
xerial/CurrencyData.py
xerial/DBExecutableSession.py
xerial/DBMigration.py
xerial/DBSessionBase.py
xerial/DBSessionPool.py
xerial/DateColumn.py
xerial/DateTimeColumn.py
xerial/DayIntervalColumn.py
xerial/ExcelWriter.py
xerial/Filter.py
xerial/FilterConjunction.py
xerial/FilterOperation.py
xerial/FloatColumn.py
xerial/ForeignKey.py
xerial/FormComponent.py
xerial/FractionColumn.py
xerial/Input.py
xerial/InputAttachment.py
xerial/InputExtractor.py
xerial/InputGroupEnum.py
xerial/IntegerColumn.py
xerial/JSONColumn.py
xerial/MSSQLDBSession.py
xerial/MariaDBSession.py
xerial/MetaDataExtractor.py
xerial/ModelClassGenerator.py
xerial/ModelGeneratorBase.py
xerial/Modification.py
xerial/ModificationType.py
xerial/MultiPoint.py
xerial/MultiPointColumn.py
xerial/OptionEnum.py
xerial/OracleDBSession.py
xerial/OracleModelGenerator.py
xerial/Point.py
xerial/PointColumn.py
xerial/PostgresDBSession.py
xerial/PrimitiveStructure.py
xerial/RawMigration.py
xerial/Record.py
xerial/RoundRobinConnector.py
xerial/SQLiteDBSession.py
xerial/StringColumn.py
xerial/TimeColumn.py
xerial/TimeIntervalColumn.py
xerial/Vendor.py
xerial/__init__.py
xerial/cli/XerialBackupEnablerCLI.py
xerial/cli/XerialGeneratorCLI.py
xerial/cli/XerialMigrationCLI.py
xerial/cli/XerialModelExtractorCLI.py
xerial/cli/XerialPrimaryCreatorCLI.py
xerial/cli/__init__.py
xerial/exception/ChangeTypeException.py
xerial/exception/DateTimeToDateException.py
xerial/exception/ExceptionCode.py
xerial/exception/ModificationException.py
xerial/exception/TypeIncompatibleException.py
xerial/exception/XerialException.py
xerial/exception/__init__.py
xerial/filter/CheckBoxFilter.py
xerial_orm-0.9.13.dist-info/LICENSE.txt
xerial_orm-0.9.13.dist-info/METADATA
xerial_orm-0.9.13.dist-info/WHEEL
xerial_orm-0.9.13.dist-info/entry_points.txt
xerial_orm-0.9.13.dist-info/top_level.txt
xerial_orm-0.9.13.dist-info/RECORD
