Metadata-Version: 2.1
Name: xerial-orm
Version: 0.9.13
Summary: A Simple but Powerful Object Rational Mapping (ORM) library.
Author: Suppakorn Rakna
Author-email: Kittipong Piyawanno <k.piyawanno@gmailc.com>
Project-URL: Homepage, https://github.com/Piyawanno/Xerial
Project-URL: Documentation, https://github.com/Piyawanno/Xerial/tree/main/document
Project-URL: Repository, https://github.com/Piyawanno/Xerial
Project-URL: Issues, https://github.com/Piyawanno/Xerial/issues
Project-URL: Changelog, https://github.com/Piyawanno/Xerial/blob/main/CHANGELOG.md
Keywords: database,orm
Classifier: Development Status :: 4 - Beta
Classifier: Intended Audience :: Developers
Classifier: Topic :: Database
Classifier: Topic :: Software Development :: Libraries :: Python Modules
Classifier: License :: OSI Approved :: GNU General Public License v2 or later (GPLv2+)
Classifier: Programming Language :: Python :: 3
Classifier: Programming Language :: Python :: 3.6
Classifier: Programming Language :: Python :: 3.7
Classifier: Programming Language :: Python :: 3.8
Classifier: Programming Language :: Python :: 3.9
Classifier: Programming Language :: Python :: 3.10
Classifier: Programming Language :: Python :: 3.11
Classifier: Programming Language :: Python :: 3.12
License-File: LICENSE.txt
Requires-Dist: psycopg2-binary
Requires-Dist: asyncpg
Requires-Dist: aiosqlite
Requires-Dist: pyodbc
Requires-Dist: aioodbc
Requires-Dist: shapely
Requires-Dist: packaging
Requires-Dist: tabulate
Requires-Dist: xlsxwriter
